asset_tags_service/__init__.py
asset_tags_service/asset_tags_service_client.py
asset_tags_service/apis/__init__.py
asset_tags_service/apis/asset_tags_api.py
asset_tags_service/models/__init__.py
asset_tags_service/models/asset_tag_assign_request.py
asset_tags_service/models/asset_tag_group.py
asset_tags_service/models/asset_tag_remove_request.py
asset_tags_service/models/asset_tags.py
asset_tags_service/models/bulk_asset_tag_request.py
commons/__init__.py
commons/http/__init__.py
commons/http/client/__init__.py
commons/http/client/base_client.py
commons/http/client/dataos_consumer.py
commons/http/client/hadler.py
commons/utils/__init__.py
commons/utils/constants.py
commons/utils/env_helper.py
commons/utils/helper.py
commons/utils/logger.py
dataos_sdk_py-1.0.6.dist-info/licenses/LICENSE
depot_service/__init__.py
depot_service/depot_service_client.py
depot_service/apis/__init__.py
depot_service/apis/dataset_api.py
depot_service/apis/depot_api.py
depot_service/apis/resolver_api.py
depot_service/apis/secret_api.py
depot_service/models/__init__.py
depot_service/models/ds_models.py
depot_service/models/models.py
depot_service/test/__init__.py
depot_service/test/test_dataset_api.py
depot_service/test/test_depot_api.py
depot_service/test/test_resolve_api.py
depot_service/test/test_secret_api.py
gateway/__init__.py
gateway/gateway_client.py
gateway/apis/__init__.py
gateway/apis/cluster_api.py
gateway/apis/query_api.py
gateway/apis/security_api.py
gateway/models/__init__.py
gateway/models/gateway_models.py
gateway/test/__init__.py
gateway/test/test_security_api.py
heimdall/__init__.py
heimdall/heimdall_client.py
heimdall/apis/__init__.py
heimdall/apis/authorize_api.py
heimdall/apis/collections_api.py
heimdall/apis/data_policy_api.py
heimdall/apis/policy_api.py
heimdall/apis/policy_enforcement_provider_api.py
heimdall/apis/policy_use_case_grant_requests.py
heimdall/apis/policy_use_case_grants_api.py
heimdall/apis/roles_api.py
heimdall/apis/secret_api.py
heimdall/apis/tags_api.py
heimdall/apis/tokens_api.py
dataos_sdk_py-1.0.6.dist-info/METADATA
dataos_sdk_py-1.0.6.dist-info/WHEEL
dataos_sdk_py-1.0.6.dist-info/top_level.txt
dataos_sdk_py-1.0.6.dist-info/RECORD
