Metadata-Version: 2.4
Name: dataos-sdk-py
Version: 1.0.6
Summary: A description of the dataos-sdk-py package
Home-page: https://bitbucket.org/rubik_/dataos-sdk-py
Author: devendrasr
Author-email: TMDC Labs <labs@tmdc.io>
License: Programming Language :: Python :: 3 License :: OSI Approved :: MIT License Operating System :: OS Independent
Classifier: Programming Language :: Python :: 3
Classifier: License :: OSI Approved :: MIT License
Classifier: Operating System :: OS Independent
Requires-Python: >=3.7
License-File: LICENSE
Requires-Dist: requests>=2.32.3
Requires-Dist: pydantic>=2.9.2
Requires-Dist: uplink>=0.9.7
Dynamic: author
Dynamic: home-page
Dynamic: license-file
Dynamic: requires-python
